po_sync/__init__.py
po_sync/__main__.py
po_sync/cli.py
po_sync/core.py
po_sync-1.0.0.dist-info/licenses/LICENSE
po_sync-1.0.0.dist-info/METADATA
po_sync-1.0.0.dist-info/WHEEL
po_sync-1.0.0.dist-info/entry_points.txt
po_sync-1.0.0.dist-info/top_level.txt
po_sync-1.0.0.dist-info/RECORD
