Metadata-Version: 2.4
Name: po_sync
Version: 1.0.0
Summary: PoSync is an open-source CLI tool that automatically syncs .po file msgid keys with applied corrections and updates the source code at the exact lines referenced in the .po, eliminating tedious manual replacements.
Author-email: David Patiashvili <stratagem.david@gmail.com>
License-Expression: Apache-2.0
Project-URL: Homepage, https://github.com/davaxi/po_sync
Project-URL: Issues, https://github.com/davaxi/po_sync/issues
Classifier: Programming Language :: Python :: 3
Classifier: Operating System :: OS Independent
Requires-Python: >=3.9
License-File: LICENSE
Requires-Dist: polib>=1.2.0
Requires-Dist: tabulate>=0.9.0
Dynamic: license-file
